{
    "kannada_title": "\u0ca8\u0c82\u0ca6\u0ca8\u0c82\u0ca6\u0ca8 \u0caa\u0cbe\u0cb9\u0cbf \u0c97\u0cc1\u0ca3\u0cb5\u0cc3\u0c82\u0ca6",
    "english_title": "Nandanandana pahi gunavrunda",
    "kannada": "\u0ca8\u0c82\u0ca6\u0ca8\u0c82\u0ca6\u0ca8 \u0caa\u0cbe\u0cb9\u0cbf \u0c97\u0cc1\u0ca3\u0cb5\u0cc3\u0c82\u0ca6\n\u0cb8\u0cc1\u0c82\u0ca6\u0cb0 \u0cb0\u0cc2\u0caa \u0c97\u0ccb\u0cb5\u0cbf\u0c82\u0ca6 \u0cae\u0cc1\u0c95\u0cc1\u0c82\u0ca6 || PA ||\n\n\u0ca6\u0cbf\u0ca8\u0c95\u0cb0\u0cad\u0cb5\u0caa\u0cbe\u0cb2 \u0c95\u0ca8\u0c95\u0cbe\u0c82\u0c95\u0cbf\u0ca4 \u0c9a\u0cc7\u0cb2\n\u0c9c\u0ca8\u0c95\u0c9c\u0cbe\u0cb2\u0ccb\u0cb2 \u0c9c\u0ca8\u0c95\u0cbe\u0ca8\u0cc1\u0c95\u0cc2\u0cb2 || 1 ||\n\n\u0caa\u0cb5\u0ca8\u0c9c \u0caa\u0cb0\u0cbf\u0cb5\u0cbe\u0cb0 \u0caf\u0cb5\u0ca8\u0cb5\u0cbf\u0ca6\u0cbe\u0cb0\n\u0ca8\u0cb5\u0cb0\u0ca4\u0ccd\u0ca8\u0cb9\u0cbe\u0cb0 \u0ca8\u0cb5\u0ca8\u0cc0\u0ca4\u0c9a\u0ccb\u0cb0 || 2 ||\n\n\u0ca4\u0cc1\u0c82\u0c97 \u0cb5\u0cbf\u0cb9\u0c82\u0c97\u0ca4\u0cc1\u0cb0\u0c82\u0c97 \u0ca6\u0caf\u0cbe\u0caa\u0cbe\u0c82\u0c97\n\u0cb0\u0c82\u0c97\u0cb5\u0cbf\u0ca0\u0cb2 \u0cad\u0cb5\u0cad\u0c82\u0c97 \u0cb6\u0cc1\u0cad\u0cbe\u0c82\u0c97 || 3 ||\n\n",
    "english": "Nandanandana p\u0101hi gu\u1e47avr\u0325inda\nsundara r\u016bpa g\u014dvinda mukunda || PA ||\n\nDinakarabhavap\u0101la kanak\u0101\u1e45kita ch\u0113la\njanakaj\u0101l\u014dla janak\u0101nuk\u016bla || 1 ||\n\npavanaja pariv\u0101ra yavanavid\u0101ra\nnavaratnah\u0101ra navan\u012btach\u014dra || 2 ||\n\ntu\u1e45ga viha\u1e45gatura\u1e45ga dayapanga\nrangavithala bhavabhanga shubhanga || 3 ||\n\n",
    "media": "https://www.youtube.com/watch?v=AVKzdNaEvPU",
    "tags": [
        "dasara padagalu",
        "krishna song",
        "krishna"
    ]
}