{
    "meta": "",
    "kannada": [
        [
            "\u0caa\u0cbe\u0cb0\u0ccd\u0cb5\u0ca4\u0cbf \u0caa\u0cbe\u0cb2\u0cbf\u0cb8\u0cc6\u0ca8\u0ccd\u0ca8 \u0cae\u0cbe\u0ca8\u0cbf\u0ca8\u0cbf \u0cb0\u0ca8\u0ccd\u0ca8\u0cc6\u00a0\u00a0\u00a0\u00a0\u00a0 \u00a0 \u00a0\u00a0\u00a0 \u0964\u0964\u0caa\u0965"
        ],
        [
            "\u0caa\u0cbe\u0cb0\u0ccd\u0cb5\u0ca4\u0cbf \u0cad\u0c95\u0ccd\u0ca4\u0cb0 \u0cb8\u0cbe\u0cb0\u0ca5\u0cbf \u0cb5\u0c82\u0ca6\u0cbf\u0ca4\u0cc6",
            "\u0cb8\u0cc1\u0cb0\u0caa\u0ca4\u0cbf \u0c97\u0c9c\u0cae\u0cc1\u0c96 \u0cae\u0cc2\u0cb0\u0cc1\u0ca4\u0cbf \u0cae\u0cbe\u0ca4\u0cc6\u00a0\u00a0\u00a0\u00a0 \u00a0\u00a0 \u0964\u0964\u0ce7\u0964\u0964"
        ],
        [
            "\u0cae\u0ca8\u0ca6\u0cad\u0cbf\u0cae\u0cbe\u0ca8\u0cbf\u0caf\u0cc7 \u0ca8\u0cc6\u0ca8\u0cc6\u0cb5\u0cc6\u0ca8\u0cc1 \u0ca8\u0cbf\u0ca8\u0ccd\u0ca8",
            "\u0c85\u0ca8\u0cc1\u0cb8\u0cb0\u0cbf\u0cb8\u0cc6\u0ca8\u0ccd\u0ca8\u0ca8\u0cc1 \u0c85\u0c82\u0cac\u0cc1\u0c9c \u0caa\u0cbe\u0ca3\u0cbf\u00a0\u00a0\u00a0\u00a0\u00a0\u00a0 \u00a0 \u00a0\u00a0\u00a0\u00a0\u00a0 \u0964\u0964\u0ce8\u0964\u0964"
        ],
        [
            "\u0cae\u0c82\u0c97\u0cb3\u0cc6 \u0cae\u0cc3\u0ca1\u0ca8 \u0c85\u0c82\u0ca4\u0cb0\u0c82\u0c97\u0cb3\u0cc7 \u0cb9\u0cb0\u0cbf\u0caa\u0ca6",
            "\u0cad\u0cc3\u0c82\u0c97\u0cb3\u0cc6 \u0ca4\u0cca\u0c82\u0c97\u0cb3\u0cc7 \u0caa\u0ca8\u0ccd\u0ca8\u0c97 \u0cb5\u0cc7\u0ca3\u0cbf\u00a0\u00a0\u00a0\u00a0\u00a0\u00a0\u00a0\u00a0\u00a0\u00a0\u00a0\u00a0 \u0964\u0964\u0ce9\u0964\u0964"
        ],
        [
            "\u0c97\u0cc1\u0ca3 \u0caa\u0cc2\u0cb0\u0ccd\u0ca3 \u0cb5\u0cc7\u0ca3\u0cc1 \u0c97\u0ccb\u0caa\u0cbe\u0cb2 \u0cb5\u0cbf\u0ca0\u0cb2\u0ca8\u0ccd\u0ca8",
            "\u0c95\u0cbe\u0ca3\u0cbf\u0cb8\u0cbf \u0c95\u0cca\u0ca1\u0cc1\u0cb5\u0c82\u0ca4 \u0cb6\u0cc2\u0cb2\u0cbf\u0caf \u0cb0\u0cbe\u0ca3\u0cbf\u00a0\u00a0\u00a0\u00a0\u00a0\u00a0\u00a0\u00a0\u00a0 \u0964\u0964\u0cea\u0964\u0964"
        ]
    ],
    "english": [
        [
            "Parvati palisenna maninirenna |"
        ],
        [
            "Parvati bakutara saarathi vandipe |",
            "surapati gajamuka muruti mate |"
        ],
        [
            "Manadabhimaniye nenevanu",
            "ninnanu anugrahisennanu ambuja pani | 1 |"
        ],
        [
            "Mangale mrudha nantarangale hari pada |",
            "brungale tungale pannanga veni | 2 |"
        ],
        [
            "Gunapurna venu gopala vithalana",
            "kaanisi koduvanta shuliya\u00a0 rani | 3 |"
        ]
    ],
    "media": "https://www.youtube.com/watch?v=58JFh3bntlY",
    "tag": [
        "kannada devotional song"
    ],
    "categories": [],
    "kannada_title": "\u0caa\u0cbe\u0cb0\u0ccd\u0cb5\u0ca4\u0cbf \u0caa\u0cbe\u0cb2\u0cbf\u0cb8\u0cc6\u0ca8\u0ccd\u0ca8 \u0cae\u0cbe\u0ca8\u0cbf\u0ca8\u0cbf",
    "english_title": "Parvati palisenna maninirenna",
    "tags": []
}